[
  {
    "category": "risk-discipline",
    "title": "仓位决策",
    "scenario": "账户：$10,000 模拟。出现一个你喜欢的形态：入场 100，结构显示失效位在 95。你想进场。接下来三个决策决定了这是一笔交易还是一场赌博。",
    "checkpoints": [
      {
        "question": "你如何确定仓位？",
        "options": [
          {
            "id": "formula",
            "label": "风险账户的 1%：($10,000 x 1%) / (100 - 95) = 20 股",
            "feedback": "正确。先选风险，仓位由此推导。是止损距离——而非信念——决定股数。"
          },
          {
            "id": "round",
            "label": "买 100 股——一个看起来有分量的好整数",
            "feedback": "按整数定仓位意味着你的风险由图表稍后决定：这里 100 股冒了账户 5% 的风险，是政策的五倍。"
          },
          {
            "id": "allin",
            "label": "用满购买力——这形态太好了，不该浪费",
            "feedback": "满仓定量让单根不利K线就能致命。这正是终结账户的那种习惯。"
          }
        ]
      },
      {
        "question": "止损放在哪里？",
        "options": [
          {
            "id": "structure",
            "label": "放在 95，即让论点失效的位置之下",
            "feedback": "正确。止损住在想法被证伪之处，而非住在一个感觉可接受的金额上。"
          },
          {
            "id": "tight",
            "label": "放在 99——止损更紧我就能买更多股",
            "feedback": "放在寻常噪声里的止损不是风控，是捐款。你把仓位放大，只为更频繁地输。"
          },
          {
            "id": "none",
            "label": "不设止损——我盯着，必要时手动出场",
            "feedback": "无人看管的屏幕、一场会议、一个跳空：「心理止损」恰在最需要时失效。失效位未定义，意味着风险无界。"
          }
        ]
      },
      {
        "question": "价格跌到 96.20 后停滞。你在 95 的止损完好。现在怎么办？",
        "options": [
          {
            "id": "hold",
            "label": "什么都不做。计划完好，直到 95 成交",
            "feedback": "正确。失效位之上的回调，按定义就是噪声。做决定的是计划，而非不适。"
          },
          {
            "id": "widen",
            "label": "把止损挪到 93，给它更多空间",
            "feedback": "放宽止损会把一笔计划内的小亏变成计划外的大亏。宪章存在，正是为了禁止这件事。"
          },
          {
            "id": "panic",
            "label": "现在就出——保住剩下的",
            "feedback": "在失效位之上出场，意味着你的胃否决了你的计划。你留住了钱，却训练了弃用计划的习惯。"
          }
        ]
      }
    ]
  },
  {
    "category": "process-quality",
    "title": "飞行前检查",
    "scenario": "你在上升趋势中发现一个回调。图表看着对。在订单进去之前，流程分数就已经在书写。",
    "checkpoints": [
      {
        "question": "确认之前，下单票据上要写什么？",
        "options": [
          {
            "id": "full",
            "label": "止损、目标、风险%、书面理由，以及我此刻的感受",
            "feedback": "正确。计划的五个字段就是整个流程分数：失效位、出场、仓位、论点、心态。"
          },
          {
            "id": "partial",
            "label": "止损和目标——理由从图表上一看就懂",
            "feedback": "今天「一看就懂」的论点，到下周复盘时已无法辨读。未写下的理由得零分，也教不会任何东西。"
          },
          {
            "id": "speed",
            "label": "只写入场——先成交，再规划，价格不等人",
            "feedback": "事后规划就是从不规划。在定义风险之前入场，是流程分数最大的扣分项。"
          }
        ]
      },
      {
        "question": "你的书面理由写着「看着像要涨」。够了吗？",
        "options": [
          {
            "id": "specific",
            "label": "不够——重写：「ADX 确认的上升趋势中回调至 EMA20，成交量在收缩」",
            "feedback": "正确。论点要点出结构、状态，以及什么会打破它。「看着像要涨」既无法复盘，也无从学习。"
          },
          {
            "id": "fine",
            "label": "行了——我知道我什么意思",
            "feedback": "40 笔交易之后你就不知道了。日志是写给一个把一切都忘光的未来自己的信。"
          },
          {
            "id": "skip",
            "label": "理由是给分析师的——盈亏才是唯一真理",
            "feedback": "没有流程的结果是噪声。2x2 存在，正因为赚钱的坏决策是最昂贵的那种。"
          }
        ]
      },
      {
        "question": "这笔交易赚了 +2R，但你始终没挂上自己写下的止损。复盘称之为危险的成功。你的回应？",
        "options": [
          {
            "id": "accept",
            "label": "诚实记录——盈利不能为破裂的流程开脱",
            "feedback": "正确。坏决策 + 好结果，训练的是那个最终要你买单的习惯。把它叫出名字，就是解药。"
          },
          {
            "id": "argue",
            "label": "推翻它——赚就是赚",
            "feedback": "和自己的仪表盘争辩，等于废掉它的用途。下一个这样的「盈利」会被放更大仓位。"
          },
          {
            "id": "ignore",
            "label": "这周整个复盘都跳过",
            "feedback": "未复盘的交易教不会任何东西。你不去检视的危险成功，正是你会重复的那个。"
          }
        ]
      }
    ]
  },
  {
    "category": "loss-acceptance",
    "title": "止损临近",
    "scenario": "50 做多，止损 47.50，计划 -1R = $100。价格在 47.80 且在下跌。每个交易者都会遇到这一刻；少有人正确地遇到它。",
    "checkpoints": [
      {
        "question": "价格跳到 47.55。止损即将成交。你怎么做？",
        "options": [
          {
            "id": "nothing",
            "label": "什么都不做。止损是计划在起作用，不是计划在失败",
            "feedback": "正确。你买入的是确定的风险。-1R 一直都是两个计划内结果之一。"
          },
          {
            "id": "cancel",
            "label": "撤掉止损——我一出来它总是马上反弹",
            "feedback": "撤掉止损会把 $100 的计划风险变成一个无底洞。每一份爆仓尸检里都有这一步。"
          },
          {
            "id": "average",
            "label": "在这里加买，拉低保本点",
            "feedback": "在亏损交易上摊低，会拉近保本点、推远总风险。单笔交易就是这样杀死账户的。"
          }
        ]
      },
      {
        "question": "在 47.50 被止损，-1R。五分钟后价格收回 50。你怎么解读？",
        "options": [
          {
            "id": "variance",
            "label": "一笔打得漂亮的亏损——好决策，被方差夺走。记录后继续",
            "feedback": "正确。分类器正是为这种刺痛而存在：结果质量和决策质量是不同的两个轴。"
          },
          {
            "id": "broken",
            "label": "证明我的止损错了——下次用更宽的且不重算仓位",
            "feedback": "不重算仓位就放宽止损，只会抬高以美元计的亏损。若结构需要更多空间，就把仓位做小。"
          },
          {
            "id": "revenge",
            "label": "立刻在 50 重新进——它欠我的",
            "feedback": "以你上一笔亏损为理由的入场就是报复性交易。市场不记应收账款。"
          }
        ]
      },
      {
        "question": "连续三笔计划内亏损，都在止损上，都已记录。流程均分：85。要改什么？",
        "options": [
          {
            "id": "nothing2",
            "label": "结构上什么都不改——复盘找规律，保持仓位，保持系统",
            "feedback": "正确。三笔 -1R 亏损，完全在任何真实系统的寻常方差之内。每逢连亏就换系统，保证你永远没有一个系统。"
          },
          {
            "id": "halve",
            "label": "把仓位减半，直到出现一个赢家",
            "feedback": "可辩护，但三笔就这么做为时过早——而且会不对称地缩小那些为亏损买单的赢家。"
          },
          {
            "id": "abandon",
            "label": "系统坏了——今晚就找个新的",
            "feedback": "蒙特卡洛说，胜率 50% 的系统有三分之一的时间待在回撤里。系统跳来跳去，每次都把样本清零。"
          }
        ]
      },
      {
        "question": "你用止损限价单（触发 47.50，限价 47.40）而非止损单保护了一个仓位。一则隔夜消息让开盘跳空到 45.80。你的保护怎么了？",
        "options": [
          {
            "id": "unfilled",
            "label": "什么都没成交——限价那条腿需要 47.40 或更好，而价格从未在那里成交。我仍在做多，比我的「止损」低 4%",
            "feedback": "正确。这就是止损限价的陷阱：它在寻常日子里封顶滑点，却恰在你需要它的那天悄无声息地失效。这也是为什么模拟场所拒绝模拟止损限价——在收盘K线上，那笔成交只能靠捏造。"
          },
          {
            "id": "filled_at_limit",
            "label": "它在 47.40 成交了——这就是限价所保证的",
            "feedback": "限价保证价格，从不保证成交。价格跳空穿过你的窗口而未在其中成交；订单仍挂在那里、未成交，而亏损在扩大。"
          },
          {
            "id": "filled_at_open",
            "label": "它像普通止损那样在 45.80 开盘价成交了",
            "feedback": "那是普通止损单的做法：变成市价单，吞下跳空。限价那条腿恰恰阻止了那次成交。要清楚自己挂的是哪一种。"
          }
        ]
      }
    ]
  },
  {
    "category": "tilt-control",
    "title": "红色清晨",
    "scenario": "午饭前两次止损，都在计划内，都是 -1R。你注意到下巴在收紧，刷新图表变得强迫。下一个决定就是整盘棋。",
    "checkpoints": [
      {
        "question": "出现第三个形态。它很勉强——不是你的 A 级形态。会发生什么？",
        "options": [
          {
            "id": "skip",
            "label": "略过它，并记下情绪：「沮丧，想要赚回来」",
            "feedback": "正确。把状态大声叫出名字，就是及早抓住上头的方式。勉强形态 + 火热状态 = 经典的第三次亏损。"
          },
          {
            "id": "smaller",
            "label": "用一半仓位做——和冲动的折中",
            "feedback": "半仓的上头仍是上头。入场的理由是你的早晨，而非市场。"
          },
          {
            "id": "double",
            "label": "用双倍仓位做——一笔赚回整个早晨",
            "feedback": "亏后加倍是穿着连帽衫的马丁格尔。这是风控官所知最高严重度的模式。"
          }
        ]
      },
      {
        "question": "你略过了它。那个勉强形态本来会赢。你怎么归档？",
        "options": [
          {
            "id": "good",
            "label": "一个好决策。上头时略过 B 级形态是政策，而政策要在 100 笔交易上评判",
            "feedback": "正确。反事实的盈利什么都不改变：决策在做出时是对的。用结果评判被略过的交易，等于重新打开上头之门。"
          },
          {
            "id": "regret",
            "label": "证明我沮丧时应该相信直觉",
            "feedback": "一个对抗政策的样本，正是危险习惯被录用的方式。那个想要这笔交易的直觉，也想要那笔双倍仓位的报复入场。"
          },
          {
            "id": "rule_off",
            "label": "关掉每日上限规则——它在花钱",
            "feedback": "恰在护栏起作用的那一刻把它删掉，就是宪章在它唯一的考验上落败。"
          }
        ]
      },
      {
        "question": "什么样的收尾才算正确结束这场交易？",
        "options": [
          {
            "id": "ritual",
            "label": "把三个决策都记录下来，标记情绪，关掉终端",
            "feedback": "正确。这一天的价值从来不是盈亏——而是一份在恼怒下保持的干净行为记录。"
          },
          {
            "id": "watch",
            "label": "继续看盘「只是为了学习」——但不下单",
            "feedback": "上头时盯屏，正是「不下单」变成下一单的过程。学习发生在日志里，而非刷新循环里。"
          },
          {
            "id": "binge",
            "label": "待到某个赢家把这天变绿",
            "feedback": "需要一个绿色的一天，是上头在说话。日子是会计上的虚构；流程均分才是真分数。"
          }
        ]
      }
    ]
  },
  {
    "category": "journaling",
    "title": "诚实的记录",
    "scenario": "市场已收盘。三笔已执行的交易尚未记录：一笔干净的盈利、一笔草率的盈利、一笔计划内的亏损。可用十分钟的诚实。",
    "checkpoints": [
      {
        "question": "哪笔交易最先、也最深入地被记录？",
        "options": [
          {
            "id": "sloppy",
            "label": "那笔草率的盈利——追了价、没记情绪、靠运气出场",
            "feedback": "正确。草率的盈利才是危险的：被奖赏的错误会被重复。盈利比亏损更需要尸检。"
          },
          {
            "id": "loss",
            "label": "那笔亏损——教训住在亏损里",
            "feedback": "合理，但这笔亏损是计划内且干净的——它确认了系统。草率的盈利才是新信息所在之处。"
          },
          {
            "id": "best",
            "label": "那笔干净的盈利——以一个高潮收尾",
            "feedback": "只记录让你脸上有光的，产生的是私人日记，而非数据集。"
          }
        ]
      },
      {
        "question": "关于那笔草率盈利，有用的笔记会怎么写？",
        "options": [
          {
            "id": "honest",
            "label": "「它开始动后，我追在计划入场上方 0.8% 处。FOMO。还是赢了——已标记为危险习惯」",
            "feedback": "正确。具体行为、命名情绪、诚实标签。这条笔记喂养教练的检测器和你的未来自己。"
          },
          {
            "id": "vague",
            "label": "「入场本可更好。不过结果不错」",
            "feedback": "含糊的笔记无法被聚合、检测或学习。「本可更好」描述了有史以来的每一笔交易。"
          },
          {
            "id": "victory",
            "label": "「精准命中。+1.8R。多来点这样的」",
            "feedback": "「多来点这样的」——多追几次价？这条笔记刚刚因为错误赚了一次，就为它背书。"
          }
        ]
      },
      {
        "question": "今天很漫长，第三条笔记感觉可有可无。决定吧。",
        "options": [
          {
            "id": "write",
            "label": "写下来——两句话。未记录的交易教不会任何东西",
            "feedback": "正确。完整记录的连续，比任何单条洞见更值钱。三笔写三笔，每一天。"
          },
          {
            "id": "tomorrow",
            "label": "明天用清醒的头脑做",
            "feedback": "明天的记忆是被后见之明装点过的虚构。入场那一刻的状态已经在蒸发。"
          },
          {
            "id": "skip2",
            "label": "略过——只是笔计划内亏损，没什么可学",
            "feedback": "计划内亏损确认了系统在运转——那份确认就是数据。跳过日志是个检测器，自有其道理。"
          }
        ]
      }
    ]
  },
  {
    "category": "selectivity",
    "title": "安静的盘面",
    "scenario": "周二，11:40。你今天做了一笔好交易。盘面变得安静而震荡。你的每日上限是 3。光标在悬停。",
    "checkpoints": [
      {
        "question": "没有任何东西符合你的形态清单，但你「正在状态上」。现在怎么办？",
        "options": [
          {
            "id": "flat",
            "label": "保持空仓。没形态、没交易——状态不是形态",
            "feedback": "正确。最难的仓位是空仓。选择性才是优势；活跃是它的税。"
          },
          {
            "id": "hunt",
            "label": "切到 1 分钟图去找点东西",
            "feedback": "放大到噪声看起来像信号，正是「没形态」变成五个糟糕形态的过程。"
          },
          {
            "id": "boredom",
            "label": "做一笔小小的「无聊交易」以保持投入",
            "feedback": "无聊交易是上头礼貌的表亲：入场的理由是你的心情。小的坏交易训练大的坏习惯。"
          }
        ]
      },
      {
        "question": "一个真正不错的形态出现在你从未交易过的品种上。上限允许。决定吧。",
        "options": [
          {
            "id": "check",
            "label": "对新品种做完整的飞行前检查——流动性、点差、波动率——通过则按正常仓位",
            "feedback": "正确。新品种值得同样的流程，外加一次场所核查。做对的广度，是判断力的多元化。"
          },
          {
            "id": "familiar",
            "label": "略过——只交易你了解的",
            "feedback": "可辩护，但把「我了解的」缩到一张图，会窄化你技能所依赖的证据。"
          },
          {
            "id": "yolo",
            "label": "立刻就做——形态就是形态",
            "feedback": "形态也许能迁移；点差、流动性和跳空行为也许不能。未经检视的场所风险，仍是风险。"
          }
        ]
      }
    ]
  },
  {
    "category": "outcome-integrity",
    "title": "2x2 的解读",
    "scenario": "每周复盘。屏幕上四笔交易：一笔靠本事的盈利、一笔打得漂亮的亏损、一笔诚实的学费、一笔危险的成功。你如何解读它们，决定了下一周长什么样。",
    "checkpoints": [
      {
        "question": "哪个象限最危险？",
        "options": [
          {
            "id": "ds",
            "label": "危险的成功——一个被市场买单的坏决策",
            "feedback": "正确。被奖赏的错误会复利：下次是更大仓位和更多自信，而账单连本带利地到来。"
          },
          {
            "id": "tuition",
            "label": "诚实的学费——亏了钱，且是个坏决策",
            "feedback": "学费很疼，但教得干净：坏流程、坏结果、清晰可读的教训。它很少被放量重复。"
          },
          {
            "id": "loss",
            "label": "打得漂亮的亏损——亏损永远是问题",
            "feedback": "把打得漂亮的亏损称作「问题」，是对结果的崇拜。那笔亏损是系统在运转。"
          }
        ]
      },
      {
        "question": "你靠本事的盈利和危险的成功都赚了同样的 +1.5R。是什么把它们分开？",
        "options": [
          {
            "id": "repeat",
            "label": "靠本事盈利的流程可以刻意重复；危险的成功是向方差租来的",
            "feedback": "正确。盈亏相同，信息相反。两者中只有一个是技能的证据。"
          },
          {
            "id": "same",
            "label": "没什么——R 就是 R",
            "feedback": "R 衡量结果，而非决策质量。若 R 就是一切，彩票中奖者就成了投资者。"
          },
          {
            "id": "luck_all",
            "label": "两个都是运气——单笔交易根本没有意义",
            "feedback": "单个结果是嘈杂的，但决策可以立即评估。这种不对称，正是流程评分的全部意义。"
          }
        ]
      },
      {
        "question": "下周唯一的纠正行动是什么？",
        "options": [
          {
            "id": "fix_ds",
            "label": "重读那笔危险成功的入场条件，写下本可挡住它的那条规则",
            "feedback": "正确。每个被检测到的模式配一条具体的、写下来的规则——这就是反馈闭环在合拢。"
          },
          {
            "id": "more_wins",
            "label": "瞄准更多盈利——提高胜率",
            "feedback": "胜率是个产出。直接去追它，通常意味着过早砍掉赢家、放宽止损——两者都具腐蚀性。"
          },
          {
            "id": "trade_more",
            "label": "多交易，好更快地把样本做大",
            "feedback": "一个更大的、未经检视的决策样本，只是更多噪声。在扩大产出之前，先修好生成器。"
          }
        ]
      }
    ]
  },
  {
    "category": "replay-mastery",
    "title": "解读回放",
    "scenario": "你即将在模拟器里跑一个历史片段。你如何使用回放，决定了它是训练判断力，还是只是消遣。",
    "checkpoints": [
      {
        "question": "回放中途，你认出了这个片段——你知道它怎么结束。诚实的做法是什么？",
        "options": [
          {
            "id": "process",
            "label": "仍然从流程出发作答：在这根K线上，一个交易者在没有后见之明时「应该」做什么？",
            "feedback": "正确。回放评判的是决策，而非预测。靠后见之明来答题，只会教你对过去正确。"
          },
          {
            "id": "exploit",
            "label": "利用这份知识——分数就是分数",
            "feedback": "你刚刚训练了「依据实盘不会有的信息行事」。分数上升；技能下降。"
          },
          {
            "id": "quit",
            "label": "退出，去找一个你不认识的片段",
            "feedback": "合理的直觉，但认出片段「就是」市场素养——纪律在于仍然从流程出发作答。"
          }
        ]
      },
      {
        "question": "你在复盘环节以 55% 不及格。下一步行动？",
        "options": [
          {
            "id": "study",
            "label": "读每个检查点的后果，研究关联课程，明天再试",
            "feedback": "正确。复盘会点出更好的一手以及为什么。间隔后的重试胜过立即的再猜。"
          },
          {
            "id": "retry_now",
            "label": "立刻重试——你现在记得正确答案了",
            "feedback": "立即重试测的是记忆，而非判断。明天通过才有意义；今晚通过只说明你短期记忆正常。"
          },
          {
            "id": "dismiss",
            "label": "不当回事——模拟器反正不是真交易",
            "feedback": "模拟器的真实程度，恰等于你在其中决策的真实程度。轻视模拟器的飞行员拿不到飞机。"
          }
        ]
      }
    ]
  },
  {
    "category": "academy-scholar",
    "title": "如何真正地学习",
    "scenario": "今晚有二十分钟给学院。目标是能在与实盘图表接触后存活下来的知识。",
    "checkpoints": [
      {
        "question": "二十分钟最好怎么用？",
        "options": [
          {
            "id": "mix",
            "label": "一节新课，然后给到期的复习卡片评分，再做它在真实K线上的实战练习",
            "feedback": "正确。获取、提取、应用——让知识在压力下可用的三连。"
          },
          {
            "id": "binge2",
            "label": "速读四节课——数量就是进展",
            "feedback": "不经提取的阅读，几天就蒸发。四节略读的课，等于把一节忘掉四次。"
          },
          {
            "id": "reread",
            "label": "再读一遍你最爱的那节课——感觉很扎实",
            "feedback": "重读感觉像流利，测起来却像零。卡片之所以存在，正因为认得出不等于回忆得起。"
          }
        ]
      },
      {
        "question": "一张复习卡片冒出来：「ATR」。你彻底一片空白。正确的评分是什么？",
        "options": [
          {
            "id": "again",
            "label": "「再来」——诚实的空白会把卡片更早排程，这正是系统在起作用",
            "feedback": "正确。诚实评分就是整个算法。一个讨好的「良好」，只会把你的无知排得更远。"
          },
          {
            "id": "peek_good",
            "label": "揭示、认出来、评「良好」——差不多够了",
            "feedback": "揭示之后的认出，不等于揭示之前的回忆。你刚刚教会了排程器别再帮你。"
          },
          {
            "id": "easy_all",
            "label": "全评「容易」，好更快清空队列",
            "feedback": "一队未学会卡片的空队列，是一场看起来干净的失败。队列不是敌人；遗忘才是。"
          }
        ]
      }
    ]
  },
  {
    "category": "consistency",
    "title": "连续记录之问",
    "scenario": "每日连续记录的第 13 天。今晚你筋疲力尽，而连续计数器正盯着你。",
    "checkpoints": [
      {
        "question": "今晚「出席」的最小诚实单位是什么？",
        "options": [
          {
            "id": "cards",
            "label": "五张复习卡片，诚实评分。小而真，胜过大而跳过",
            "feedback": "正确。连续靠最小可行的会话存活。习惯是资产；今晚的量无关紧要。"
          },
          {
            "id": "force",
            "label": "硬撑一整节课加练习——连续记录要求真功夫",
            "feedback": "英雄式的疲惫会话产生肤浅的学习和怨气。怨气杀死连续记录，比休息更狠。"
          },
          {
            "id": "fake",
            "label": "打开应用，不读就把一节课标记为完成——让计数器活着",
            "feedback": "作弊的连续衡量的是点击，而非学习。你在对唯一重要的观众撒谎。"
          }
        ]
      },
      {
        "question": "第 14 天：连续记录还是断了——你就是忘了。反应？",
        "options": [
          {
            "id": "restart",
            "label": "明天从第 1 天重启连续记录。那 13 天的学习仍是你的",
            "feedback": "正确。计数器重置；知识不会。把断掉的连续当作灾难，正是人们彻底放弃的方式。"
          },
          {
            "id": "spiral",
            "label": "系统失败了——放弃每日练习",
            "feedback": "一天没做就抹掉习惯，是全有或全无的思维——正是炸毁账户的那个认知漏洞。"
          },
          {
            "id": "backfill",
            "label": "找个办法把昨天的活动倒填日期",
            "feedback": "对自己的仪表盘作弊。若数字可以商量，它们没有一个有意义。"
          }
        ]
      }
    ]
  },
  {
    "category": "constitution",
    "title": "写出守得住的规则",
    "scenario": "你在起草你的交易宪章。你今晚写下的规则，稍后会拦下你自己的订单——为最差版本的你而写。",
    "checkpoints": [
      {
        "question": "哪条最大风险规则该进文档？",
        "options": [
          {
            "id": "one",
            "label": "每笔 1%——可存活的连亏，按设计就该无聊",
            "feedback": "正确。在 1% 下，连亏十次损失约 10%。宪章的工作，就是让破产的算术成为不可能。"
          },
          {
            "id": "five",
            "label": "5%——你是来成长的，不是来爬的",
            "feedback": "在 5% 下，七次寻常亏损就是账户的三分之一。从那以后，回撤恢复曲线毫不留情。"
          },
          {
            "id": "flex",
            "label": "「依信念灵活调整」——规则该会呼吸",
            "feedback": "带着信念逃生舱口的规则不是规则。信念恰在纪律最重要时最高。"
          }
        ]
      },
      {
        "question": "第 3 周：一笔你确信的交易，要 2% 风险才容得下它的止损。下单票据把它拦下了。决定吧。",
        "options": [
          {
            "id": "resize",
            "label": "把仓位减半，让同一个止损只花 1%——规则成立",
            "feedback": "正确。止损是结构性的；仓位才是自由变量。宪章刚刚做了它唯一的工作。"
          },
          {
            "id": "amend_now",
            "label": "现在就修改宪章以允许 2%——然后做这笔交易",
            "feedback": "在冲动之中为允许冲动而修改，不是治理，是戏服。修订发生在复盘日，绝不在交易日。"
          },
          {
            "id": "disable",
            "label": "为这一笔交易关掉强制执行",
            "feedback": "带贪睡按钮的强制系统什么都保护不了。这是最高严重度的治理失败。"
          }
        ]
      },
      {
        "question": "修改宪章的正确时机是什么时候？",
        "options": [
          {
            "id": "scheduled",
            "label": "在计划好的每月复盘上，日志打开且无持仓时",
            "feedback": "正确。规则依据证据演进，由冷静版本的你决定——绝不由那个握着持仓的你。"
          },
          {
            "id": "after_win",
            "label": "在一个大赚的一周之后——你赢得了更宽松的规则",
            "feedback": "赢后放松风险，正是危险的成功毕业成账户大小教训的方式。"
          },
          {
            "id": "never",
            "label": "永不——宪章是永恒的",
            "feedback": "从不依据证据演进的规则会变成被整批无视的遗物。计划好的修订「才是」纪律。"
          }
        ]
      }
    ]
  },
  {
    "category": "capstone",
    "title": "操作者的一小时",
    "scenario": "一小时，真实条件：一个临近止损的持仓、另一品种上一个新鲜的 A 级形态、昨天两笔未记录的交易，以及到期的复习卡片。分配你自己。",
    "checkpoints": [
      {
        "question": "头五分钟？",
        "options": [
          {
            "id": "risk_first",
            "label": "检查持仓的风险：止损在跑、仓位正确，除非 94.80 成交否则无需决策",
            "feedback": "正确。未平仓风险永远是优先级零。确认机器已上膛，然后就别去碰它。"
          },
          {
            "id": "new_first",
            "label": "那个 A 级形态——机会会过期，行政事务不会",
            "feedback": "在未平仓风险未经核实时进入新风险，正是两个 1% 仓位变成一个 4% 惊吓的方式。"
          },
          {
            "id": "pnl_first",
            "label": "刷新几次盈亏，看看自己处在什么位置",
            "feedback": "盈亏是个产出。盯着它什么都不改变，还在一个决策小时之前给结果思维上了底色。"
          }
        ]
      },
      {
        "question": "A 级形态有效，且你的每日上限允许。持仓距止损 0.4R。你做这笔新交易吗？",
        "options": [
          {
            "id": "size_aware",
            "label": "做，按正常 1% 仓位——每笔独立，两笔都在政策内，组合热度已核查",
            "feedback": "正确。在已核查的热度上限内，两个独立的 1% 风险，是系统满负荷运转，而非超载。"
          },
          {
            "id": "wait_out",
            "label": "不做——绝不同时持两个仓",
            "feedback": "可存活但武断：若热度上限和仓位是真的，只做串行交易是出于恐惧而让系统的容量闲置。"
          },
          {
            "id": "double_up",
            "label": "做，按 2%——反正第一笔基本已经输了",
            "feedback": "「基本已经输了」是在提前花掉一个还没成交的止损，然后再用上头的算术把敞口翻倍。"
          }
        ]
      },
      {
        "question": "还剩二十分钟。是补日志，还是做复习卡片？",
        "options": [
          {
            "id": "journal_first",
            "label": "趁语境还活着记录那两笔交易，卡片用剩下的时间",
            "feedback": "正确。日志的语境以小时衰减；卡片的排程能容一天。易腐的活先做。"
          },
          {
            "id": "cards_first",
            "label": "先做卡片——连续记录的指标可见，日志不可见",
            "feedback": "为可见的指标而牺牲有价值的那个去优化。日志喂养教练拥有的每一个检测器。"
          },
          {
            "id": "neither",
            "label": "两个都不做——不如再去找一个形态",
            "feedback": "这一小时的杠杆，从来不是第三笔交易。操作者拿的薪水，是为那无聊的二十分钟。"
          }
        ]
      }
    ]
  }
]
