{
  "levels": {
    "novice": {
      "title": "कैंडल से सिग्नल तक",
      "description": "बुनियादी शब्दावली बनाएं। अंत तक आप कोई भी कैंडलस्टिक पढ़ सकेंगे, रुझान पहचानेंगे, सपोर्ट/रेज़िस्टेंस ढूंढेंगे, और अपना पहला QuantGlass सिग्नल समझ सकेंगे।"
    },
    "intermediate": {
      "title": "संकेतक और जोखिम",
      "description": "गहराई में जाएं: मूविंग एवरेज, RSI मोमेंटम, ATR-आधारित स्टॉप सेटिंग, जोखिम:इनाम गणित, और पोज़िशन साइज़िंग। इस मॉड्यूल के बाद आप QuantGlass सिग्नल का हर नंबर खुद निकाल सकते हैं।"
    },
    "advanced": {
      "title": "इंजन की गहराई में",
      "description": "समझें कि सिग्नल इंजन कैसे सोचता है: मार्केट रिजीम, MACD, बोलिंगर बैंड, ईमानदार बैकटेस्टिंग, और पूरा confidence_basis व्युत्पन्न। आप समझा सकेंगे कि कोई भी सिग्नल क्यों बना।"
    },
    "expert": {
      "title": "बनाएं और कैलिब्रेट करें",
      "description": "वॉक-फॉरवर्ड OOS सत्यापन, एम्पिरिकल बेज़ कैलिब्रेशन, कस्टम संकेतक और रणनीति एक्सटेंशन लिखना, और सब कुछ एक अनुशासित निजी ट्रेडिंग योजना में जोड़ना।"
    }
  },
  "tracks": [
    {
      "id": "market-foundations",
      "title": "मार्केट की बुनियाद",
      "description": "उपकरण, एक्सचेंज, सत्र, ऑर्डर प्रकार, स्प्रेड और लिक्विडिटी — किसी भी चार्ट को पढ़ने से पहले बाज़ार वास्तव में कैसे काम करते हैं।"
    },
    {
      "id": "chart-literacy",
      "title": "चार्ट साक्षरता",
      "description": "कोई भी कैंडलस्टिक चार्ट पढ़ें: कैंडल, रुझान, सपोर्ट/रेज़िस्टेंस और वॉल्यूम।"
    },
    {
      "id": "first-signal",
      "title": "आपका पहला सिग्नल",
      "description": "एक QuantGlass सिग्नल को आद्योपांत पढ़ें और अपना पहला पेपर ट्रेड लगाएं।"
    },
    {
      "id": "indicator-mastery",
      "title": "संकेतक महारत",
      "description": "हर अंतर्निहित संकेतक परिवार — मूविंग एवरेज, RSI, MACD, Bollinger, ATR, ADX, Donchian, Keltner — ठीक जैसे इंजन उन्हें गणना करता है।"
    },
    {
      "id": "risk-position-sizing",
      "title": "जोखिम और पोज़िशन साइज़िंग",
      "description": "R-मल्टीपल, ATR-आधारित स्टॉप, पोज़िशन साइज़िंग, और पोर्टफोलियो हीट।"
    },
    {
      "id": "trade-planning",
      "title": "ट्रेड योजना और जर्नलिंग",
      "description": "प्रवेश, निकास, अमान्यता, और एक लिखित योजना व जर्नल का अनुशासन।"
    },
    {
      "id": "market-regimes",
      "title": "मार्केट रिजीम",
      "description": "ट्रेंडिंग, रेंजिंग और वोलाटाइल रिजीम — और वही सेटअप हर एक में अलग व्यवहार क्यों करता है।"
    },
    {
      "id": "strategy-families",
      "title": "रणनीति परिवार",
      "description": "ट्रेंड पुलबैक, ब्रेकआउट रीटेस्ट, मीन रिवर्जन, मोमेंटम — इंजन के वास्तविक सेटअप डिटेक्टरों से जुड़े।"
    },
    {
      "id": "statistical-honesty",
      "title": "बैकटेस्टिंग और सांख्यिकीय ईमानदारी",
      "description": "इन-सैंपल बनाम आउट-ऑफ-सैंपल, ओवरफिटिंग, वॉक-फॉरवर्ड, एक्सपेक्टेंसी, शार्प, सॉर्टिनो, प्रॉफिट फैक्टर।"
    },
    {
      "id": "execution-costs",
      "title": "निष्पादन और लागत",
      "description": "फीस, स्लिपेज, लिक्विडिटी और आंशिक फिल — जहां पेपर परिणाम और लाइव परिणाम अलग होते हैं।"
    },
    {
      "id": "trading-psychology",
      "title": "ट्रेडिंग मनोविज्ञान",
      "description": "पूर्वाग्रह, टिल्ट, बदला ट्रेडिंग, और वे दिनचर्याएं जो योजना को बरकरार रखती हैं।"
    },
    {
      "id": "quant-validation",
      "title": "मात्रात्मक सत्यापन",
      "description": "कन्फॉर्मल प्रेडिक्शन, कैलिब्रेशन, एम्पिरिकल बेज़ श्रिंकेज, और मोंटे कार्लो ड्रॉडाउन।"
    },
    {
      "id": "building-extensions",
      "title": "एक्सटेंशन बनाना",
      "description": "QuantGlass एक्सटेंशन SDK के साथ कस्टम संकेतक और रणनीतियां लिखें।"
    },
    {
      "id": "ai-assisted-research",
      "title": "AI-सहायित अनुसंधान",
      "description": "तथ्य-संरक्षित कथन, संरचित आउटपुट, और MCP वर्कफ़्लो — AI का उपयोग बिना उसे नंबर गढ़ने दिए।"
    },
    {
      "id": "going-live",
      "title": "लाइव होने की तैयारी",
      "description": "ब्रोकर प्लंबिंग, की कस्टडी, और सुरक्षा गेट। केवल शैक्षिक — कभी वित्तीय सलाह नहीं।"
    },
    {
      "id": "scam-defense",
      "title": "घोटाला रक्षा",
      "description": "नए ट्रेडरों को निशाना बनाने वाले घोटालों को पहचानें और अस्वीकार करें: नकली गुरु, सिग्नल बेचने वाले, फ़िशिंग, और सोशल-इंजीनियरिंग योजनाएं।"
    },
    {
      "id": "leverage-margin",
      "title": "मार्जिन, लीवरेज और शॉर्ट सेलिंग",
      "description": "उधार ली गई खरीद शक्ति, परिसमापन गणित, शॉर्ट यांत्रिकी, और प्रवर्धन दोनों तरफ क्यों काटता है। केवल शैक्षिक — QuantGlass स्वयं स्पॉट, पेपर-प्रथम है।"
    },
    {
      "id": "options-foundation",
      "title": "ऑप्शंस की नींव",
      "description": "कॉल, पुट, प्रीमियम, समय क्षय, और खरीदार/विक्रेता विषमता — ऑप्शंस समझने और यह जानने के लिए पर्याप्त कि वे इंजन दायरे से बाहर क्यों हैं।"
    },
    {
      "id": "fundamentals",
      "title": "ट्रेडरों के लिए फंडामेंटल",
      "description": "आय, टोकनॉमिक्स, और कैटलिस्ट — फंडामेंटल तकनीकी ट्रेडरों के लिए वोलैटिलिटी संदर्भ के रूप में, मूल्यांकन कोर्स के रूप में नहीं।"
    },
    {
      "id": "macro-intermarket",
      "title": "मैक्रो और इंटरमार्केट",
      "description": "दरें, डॉलर, लिक्विडिटी चक्र, और क्रॉस-एसेट सहसंबंध — हर चार्ट के नीचे की लहरें।"
    },
    {
      "id": "microstructure",
      "title": "मार्केट माइक्रोस्ट्रक्चर",
      "description": "ऑर्डर वास्तव में कैसे मिलते हैं: नीलामी, मेकर और टेकर, ऑर्डर फ्लो, और टिक-दर-टिक कीमत को क्या हिलाता है।"
    },
    {
      "id": "risk-officer",
      "title": "जोखिम-अधिकारी मोड",
      "description": "ट्रेडर को जोखिम कार्यालय से अलग करना: सीमाएं नीति के रूप में, उल्लंघन समीक्षा, और पूंजी-संरक्षण सिद्धांत।"
    },
    {
      "id": "pro-workflow",
      "title": "पेशेवर वर्कफ़्लो",
      "description": "ऑपरेटर का लूप: दैनिक प्रक्रिया, अनुसंधान पाइपलाइन, R-आधारित रिपोर्टिंग, और संपूर्ण-ट्रेडर संश्लेषण।"
    }
  ]
}
